cars-1.0.0.dist-info/WHEEL
cars-1.0.0.dist-info/entry_points.txt
cars-1.0.0.dist-info/METADATA
cars-1.0.0.dist-info/RECORD
cars/cars.py
cars/devibrate.py
cars/extractroi.py
cars/starter.py
cars/bundleadjustment.py
cars/__init__.py
cars/conf/input_parameters.py
cars/conf/mask_cst.py
cars/conf/__init__.py
cars/conf/geoid/egm96.grd
cars/conf/geoid/egm96.grd.hdr
cars/applications/application_template.py
cars/applications/application_constants.py
cars/applications/application.py
cars/applications/__init__.py
cars/applications/sparse_matching/sparse_matching_wrappers.py
cars/applications/sparse_matching/abstract_sparse_matching_app.py
cars/applications/sparse_matching/sparse_matching_algo.py
cars/applications/sparse_matching/sparse_matching_constants.py
cars/applications/sparse_matching/__init__.py
cars/applications/sparse_matching/sift_app.py
cars/applications/grid_correction/grid_correction_app.py
cars/applications/grid_correction/abstract_grid_correction_app.py
cars/applications/grid_correction/__init__.py
cars/applications/dem_generation/abstract_dem_generation_app.py
cars/applications/dem_generation/dem_generation_algo.py
cars/applications/dem_generation/bulldozer_dem_app.py
cars/applications/dem_generation/dem_generation_constants.py
cars/applications/dem_generation/dem_generation_wrappers.py
cars/applications/dem_generation/__init__.py
cars/applications/dem_generation/bulldozer_config/base_config.yaml
cars/applications/dsm_filling/abstract_dsm_filling_app.py
cars/applications/dsm_filling/border_interpolation_app.py
cars/applications/dsm_filling/bulldozer_filling_app.py
cars/applications/dsm_filling/__init__.py
cars/applications/dsm_filling/exogenous_filling_app.py
cars/applications/dsm_filling/bulldozer_config/base_config.yaml
cars/applications/resampling/resampling_algo.py
cars/applications/resampling/abstract_resampling_app.py
cars/applications/resampling/resampling_wrappers.py
cars/applications/resampling/bicubic_resampling_app.py
cars/applications/resampling/__init__.py
cars/applications/resampling/resampling_constants.py
