Metadata-Version: 2.1
Name: cars
Version: 1.0.0
Summary: A satellite multi view stereo pipeline
Keywords: cars,3D,DEM,pandora,photogrammetry
Author-Email: CNES <cars@cnes.fr>
Classifier: Development Status :: 4 - Beta
Classifier: Intended Audience :: Developers
Classifier: Intended Audience :: End Users/Desktop
Classifier: Intended Audience :: Science/Research
Classifier: Environment :: Console
Classifier: Topic :: Software Development :: Libraries :: Python Modules
Classifier: License :: OSI Approved :: Apache Software License
Classifier: Operating System :: OS Independent
Classifier: Programming Language :: Python
Classifier: Programming Language :: Python :: 3.10
Project-URL: Documentation, https://cars.readthedocs.io/en/latest/
Project-URL: Repository, https://github.com/CNES/cars
Requires-Python: >=3.10
Requires-Dist: numpy>=1.17.0
Requires-Dist: scipy!=1.10.0,>=1.7.1
Requires-Dist: scikit-image<0.26.0
Requires-Dist: matplotlib
Requires-Dist: affine
Requires-Dist: rasterio>=1.3.0
Requires-Dist: dask>=2021.10.0
Requires-Dist: distributed>=2021.10.0
Requires-Dist: dask-jobqueue>=0.7.3
Requires-Dist: json-checker
Requires-Dist: pyyaml
Requires-Dist: xarray
Requires-Dist: tqdm
Requires-Dist: netCDF4>=1.5.3
Requires-Dist: Shapely
Requires-Dist: Fiona
Requires-Dist: pyproj
Requires-Dist: utm
Requires-Dist: pandas
Requires-Dist: urllib3<2.0,>=1.21.1
Requires-Dist: laspy[laszip]
Requires-Dist: pandora[sgm]==1.7.2
Requires-Dist: cars-rasterize==0.2.*
Requires-Dist: cars-resample==0.1.*
Requires-Dist: cars-filter==0.2.*
Requires-Dist: vlsift==0.1.*
Requires-Dist: shareloc==0.2.12
Requires-Dist: bulldozer-dtm==1.2.*
Requires-Dist: xdem==0.2.*
Requires-Dist: geopandas<=1.0.1
Provides-Extra: dev
Requires-Dist: pytest; extra == "dev"
Requires-Dist: pytest-cov; extra == "dev"
Requires-Dist: pytest-check; extra == "dev"
Requires-Dist: pre-commit; extra == "dev"
Requires-Dist: isort>=5.8.0; extra == "dev"
Requires-Dist: black==25.*; extra == "dev"
Requires-Dist: flake8>=3.9.1; extra == "dev"
Requires-Dist: flake8-pyproject; extra == "dev"
Requires-Dist: flake8-comprehensions>=3.4.0; extra == "dev"
Requires-Dist: flake8-bugbear<24.0.0,>=21.4.3; extra == "dev"
Requires-Dist: pylint<4.0.0,>=2.8.12; extra == "dev"
Requires-Dist: setuptools_scm; extra == "dev"
Requires-Dist: virtualenv; extra == "dev"
Requires-Dist: configupdater; extra == "dev"
Requires-Dist: twine; extra == "dev"
Requires-Dist: sphinx; extra == "dev"
Requires-Dist: sphinx-rtd-theme; extra == "dev"
Requires-Dist: graphviz; extra == "dev"
Requires-Dist: dash; extra == "dev"
Requires-Dist: plotly; extra == "dev"
Requires-Dist: build; extra == "dev"
Provides-Extra: docs
Requires-Dist: astroid<4.0.0; extra == "docs"
Requires-Dist: sphinx; extra == "docs"
Requires-Dist: sphinx-rtd-theme; extra == "docs"
Requires-Dist: sphinx_autoapi; extra == "docs"
Requires-Dist: graphviz; extra == "docs"
Requires-Dist: sphinx_tabs; extra == "docs"
Requires-Dist: sphinx-copybutton; extra == "docs"
Provides-Extra: pandora-mccnn
Requires-Dist: pandora_plugin_mccnn==1.3.5; extra == "pandora-mccnn"
Provides-Extra: bundleadjustment
Requires-Dist: rpcfit; extra == "bundleadjustment"
